wikilite/__init__.py
wikilite/__main__.py
wikilite-0.1.0.dist-info/LICENSE
wikilite-0.1.0.dist-info/METADATA
wikilite-0.1.0.dist-info/WHEEL
wikilite-0.1.0.dist-info/entry_points.txt
wikilite-0.1.0.dist-info/top_level.txt
wikilite-0.1.0.dist-info/RECORD
