Metadata-Version: 2.1
Name: wikilite
Version: 0.1.0
Summary: A lightweight SQLite-based storage for Wikidict senses
Author: Yasas
Project-URL: Homepage, https://github.com/ysenarath/wikilite
Classifier: Programming Language :: Python :: 3
Classifier: License :: OSI Approved :: MIT License
Classifier: Operating System :: OS Independent
Requires-Python: >=3.7
License-File: LICENSE
Requires-Dist: tqdm>=4.65.0
